swanplot/__init__.py
swanplot/axes.py
swanplot/cname.py
swanplot/dataclass.py
swanplot/py.typed
swanplot-0.1.5.dist-info/METADATA
swanplot-0.1.5.dist-info/WHEEL
swanplot-0.1.5.dist-info/RECORD
